napari_zelda/__init__.py
napari_zelda/_reader.py
napari_zelda/_writer.py
napari_zelda/main.py
napari_zelda/napari_zelda.py
napari_zelda/plugin.py
napari_zelda-0.1.0.dist-info/LICENSE
napari_zelda-0.1.0.dist-info/METADATA
napari_zelda-0.1.0.dist-info/WHEEL
napari_zelda-0.1.0.dist-info/entry_points.txt
napari_zelda-0.1.0.dist-info/top_level.txt
napari_zelda-0.1.0.dist-info/RECORD
