Metadata-Version: 2.1
Name: napari-zelda
Version: 0.1.0
Summary: ZELDA: a 3D Image Segmentation and Parent to Child relation plugin for microscopy image analysis in napari
Home-page: UNKNOWN
Author: Rocco D'Antuono
Author-email: rocco.dantuono@hotmail.it
License: BSD-3-Clause
Platform: UNKNOWN
Classifier: Development Status :: 2 - Pre-Alpha
Classifier: Intended Audience :: Developers
Classifier: Framework :: napari
Classifier: Topic :: Software Development :: Testing
Classifier: Programming Language :: Python
Classifier: Programming Language :: Python :: 3.7
Classifier: Operating System :: OS Independent
Classifier: License :: OSI Approved :: BSD License
Requires-Python: >=3.7
License-File: LICENSE
Requires-Dist: magicgui
Requires-Dist: matplotlib
Requires-Dist: json5
Requires-Dist: napari-plugin-engine
Requires-Dist: numpy
Requires-Dist: pandas
Requires-Dist: scikit-image
Requires-Dist: scipy
Requires-Dist: QtPy
